{"question_id_null":"ID de la pregunta es vacío.","question_title_nul":"El contenido de la pregunta es vacío","choise_id_repeat":"ID de la opción repetido.","choise_data_error":"Error de datos de la opción","choise_three_twelve":"El número de la opción debería ser 3-12","xml_not_found":"No existe xml de la pregunta","question_format_error":"Error de formato de datos","next_time_come_on":"El tiempo se ha acabado.","look_left":"Consúltese la respuesta correcta a la izquierda.","you_are_good":"¡Todo correcto!","come_on":"¡Redoble los esfuerzos!","minutes":"minutos","seconds":"segundos"}